app/__init__.py
app/controllers/__init__.py
app/controllers/activate_controller.py
app/controllers/cloudhsm_mgmt_util_controller.py
app/controllers/key_mgmt_utility_controller.py
app/routes/__init__.py
app/routes/click.py
app/scripts/__init__.py
app/scripts/cloudhsm_mgmt_utility_scripts.py
app/scripts/key_mgmt_utility_scripts.py
app/scripts/terminal_scripts.py
piggy_scripts-0.0.25.dist-info/LICENSE
piggy_scripts-0.0.25.dist-info/METADATA
piggy_scripts-0.0.25.dist-info/WHEEL
piggy_scripts-0.0.25.dist-info/entry_points.txt
piggy_scripts-0.0.25.dist-info/top_level.txt
piggy_scripts-0.0.25.dist-info/RECORD
